mkdocs_gitlab_plugin/__init__.py
mkdocs_gitlab_plugin/plugin.py
mkdocs_gitlab_plugin/test.py
mkdocs_gitlab_plugin-0.1.4.dist-info/LICENSE
mkdocs_gitlab_plugin-0.1.4.dist-info/METADATA
mkdocs_gitlab_plugin-0.1.4.dist-info/WHEEL
mkdocs_gitlab_plugin-0.1.4.dist-info/entry_points.txt
mkdocs_gitlab_plugin-0.1.4.dist-info/top_level.txt
mkdocs_gitlab_plugin-0.1.4.dist-info/RECORD
